brickedit/__init__.py
brickedit/brick.py
brickedit/brm.py
brickedit/brv.py
brickedit/exceptions.py
brickedit/id.py
brickedit/var.py
brickedit/vec.py
brickedit/bt/__init__.py
brickedit/bt/base.py
brickedit/bt/classes.py
brickedit/bt/inner_properties.py
brickedit/bt/meta.py
brickedit/p/__init__.py
brickedit/p/base.py
brickedit/p/classes.py
brickedit/p/meta.py
brickedit/vhelper/__init__.py
brickedit/vhelper/color.py
brickedit/vhelper/helper.py
brickedit/vhelper/mat.py
brickedit/vhelper/time.py
brickedit/vhelper/units.py
brickedit-5.0.0.dist-info/licenses/LICENSE
brickedit-5.0.0.dist-info/METADATA
brickedit-5.0.0.dist-info/WHEEL
brickedit-5.0.0.dist-info/top_level.txt
brickedit-5.0.0.dist-info/RECORD
