Metadata-Version: 2.4
Name: brickedit
Version: 5.0.0
Summary: BrickEdit is a tool for creating and editing Brick Rigs vehicle files (.brv & .brm).
Author: MrPerruche, FateUnix29
License-Expression: GPL-3.0-or-later
Project-URL: Homepage, https://github.com/MrPerruche/BrickEdit
Project-URL: Repository, https://github.com/MrPerruche/BrickEdit
Project-URL: Issues, https://github.com/MrPerruche/BrickEdit/issues
Classifier: Development Status :: 5 - Production/Stable
Classifier: Intended Audience :: Developers
Classifier: Programming Language :: Python :: 3
Classifier: Programming Language :: Python :: 3.13
Classifier: Programming Language :: Python :: 3.14
Requires-Python: >=3.13.0
License-File: LICENSE
Dynamic: license-file
